TNSA/__init__.py
TNSA/cal.py
TNSACal-0.1.0.dist-info/METADATA
TNSACal-0.1.0.dist-info/WHEEL
TNSACal-0.1.0.dist-info/top_level.txt
TNSACal-0.1.0.dist-info/RECORD
