Metadata-Version: 2.1
Name: TNSACal
Version: 0.1.0
Summary: TNSACal is a module devloped to do complex mathematical calculations in pyhton 
Home-page: UNKNOWN
Author: TNSA
Author-email: thishyaketh@gmail.com
License: UNKNOWN
Platform: UNKNOWN
